{
  "project_info": {
    "project_number": "457256743521",
    "firebase_url": "https://friendly-chat-a948a.firebaseio.com",
    "project_id": "friendly-chat-a948a",
    "storage_bucket": "friendly-chat-a948a.appspot.com"
  },
  "client": [
    {
      "client_info": {
        "mobilesdk_app_id": "1:457256743521:android:b5d75907de594a2d",
        "android_client_info": {
          "package_name": "com.google.firebase.codelab.friendlychat"
        }
      },
      "oauth_client": [
        {
          "client_id": "457256743521-oq5csu3hjcbe8vftappo7lao0po8a076.apps.googleusercontent.com",
          "client_type": 1,
          "android_info": {
            "package_name": "com.google.firebase.codelab.friendlychat",
            "certificate_hash": "3E5696E6A6BC4D37D5C71E066B3D2C44F3494345"
          }
        },
        {
          "client_id": "457256743521-ibcrljf44c1bjijorkra4uai041qoldr.apps.googleusercontent.com",
          "client_type": 3
        }
      ],
      "api_key": [
        {
          "current_key": "AIzaSyD1EoBoFAfLHTaQ4jE7IfkJq-RwXzDQutM"
        }
      ],
      "services": {
        "analytics_service": {
          "status": 1
        },
        "appinvite_service": {
          "status": 2,
          "other_platform_oauth_client": [
            {
              "client_id": "457256743521-ibcrljf44c1bjijorkra4uai041qoldr.apps.googleusercontent.com",
              "client_type": 3
            }
          ]
        },
        "ads_service": {
          "status": 2
        }
      }
    }
  ],
  "configuration_version": "1"
}